{
  "fixtureId": "workflow-compile-digest-inclusion-changed",
  "sourceKind": "local-gate-4-contract",
  "sourceRefs": [
    "docs/gates/GATE-04.md",
    "docs/adr/0005-workflow-template-contract.md",
    "docs/adr/0006-workflow-compiler-semantics.md"
  ],
  "sourceCommit": "bc2e6e0353b2cc44f837750ed1dd5f570cc1c4fa",
  "generatorCommand": "compiler-backed local Gate 4 contract fixture",
  "generatorVersion": "gate-4-v2",
  "inputDigest": "sha256:43d24318d7751782ed6acaf97ec9fda508d2051322d27369158467c5b8a5ea4d",
  "outputDigest": "sha256:01d11568526d97018bd224042719a64198bbf1baeca010361030f8827af5fafd",
  "comparisonRules": [
    "assert-gate-4-fields",
    "assert-local-schema-closure",
    "no-php-compatibility-claim",
    "no-blueprint-conformance-claim",
    "no-ai-execution-claim",
    "no-workflow-execution-claim"
  ],
  "case": {
    "recordType": "workflow-compile",
    "negative": false,
    "outputKind": "planned-workflow-graph",
    "workflowId": "workflow-a716564df023e3c9",
    "workflowDigest": {
      "scope": "canonical-json-record",
      "schema_id": "nexus.workflow-definition",
      "schema_version": "1.0.0",
      "value": "sha256:01d11568526d97018bd224042719a64198bbf1baeca010361030f8827af5fafd"
    },
    "template": {
      "template_id": "template-rapid-review",
      "template_version": "1.0.0",
      "template_digest": "sha256:0d045018099f0564fa23952b1c3672426063c9691bc81989d872ae5f08078e33"
    },
    "protocol": {
      "status": "approved",
      "content_digest": "sha256:b05f97edad12b1c70b34f4f0e18d0d5a9a0fc2ab850ad08f8ce6fc9728adeb6d"
    },
    "schemaRefs": [
      {
        "schema_id": "nexus.workflow-template",
        "schema_version": "1.0.0"
      }
    ],
    "changedIncludedFields": [
      "workflow_id",
      "template_digest",
      "protocol_content_digest",
      "resolved_input_bindings",
      "compiled_nodes",
      "compiled_edges",
      "approval_requirements"
    ],
    "expectedSameDigest": false,
    "digestIncludes": [
      "workflow_id",
      "resolved_input_bindings",
      "compiled_nodes",
      "compiled_edges"
    ],
    "digestExcludes": [
      "workflow_execution_records",
      "approval_records"
    ],
    "nonClaims": [
      "no-php-compatibility-claim",
      "no-blueprint-conformance-claim"
    ]
  }
}
